egnn_pytorch/__init__.py
egnn_pytorch/egnn_pytorch.py
egnn_pytorch/egnn_pytorch_geometric.py
egnn_pytorch/utils.py
egnn_pytorch-0.2.8.dist-info/LICENSE
egnn_pytorch-0.2.8.dist-info/METADATA
egnn_pytorch-0.2.8.dist-info/WHEEL
egnn_pytorch-0.2.8.dist-info/top_level.txt
egnn_pytorch-0.2.8.dist-info/RECORD
